{
    "id": "urn:wmo:md:ca-eccc-msc:weather.observations.swob-realtime",
    "conformsTo": [
        "http://wis.wmo.int/spec/wcmp/2/conf/core"
    ],
    "time": {
        "interval": [
            "2010-11-11T11:11:11Z",
            ".."
        ]
    },
    "type": "Feature",
    "geometry": {
        "type": "Polygon",
        "coordinates": [
            [
                [
                    -142,
                    28
                ],
                [
                    -142,
                    82
                ],
                [
                    -52,
                    82
                ],
                [
                    -52,
                    28
                ],
                [
                    -142,
                    28
                ]
            ]
        ]
    },
    "properties": {
        "title": "Surface Weather Observations",
        "description": "Surface Observations measured at the automatic and manual stations of the Environment and Climate Change Canada and partners networks, either for a single station, or for the stations of specific provinces and territories (last 30 days)",
        "themes": [
            {
                "concepts": [
                    {
                        "id": "Weather"
                    },
                    {
                        "id": "Archives"
                    },
                    {
                        "id": "Precipitation"
                    },
                    {
                        "id": "Air temperature"
                    },
                    {
                        "id": "Humidity"
                    },
                    {
                        "id": "Snow"
                    },
                    {
                        "id": "Wind"
                    },
                    {
                        "id": "Meteorological data"
                    }
                ],
                "scheme": "https://canada.multites.net/cst"
            },
            {
                "concepts": [
                    {
                        "id": "weather",
                        "title": "Weather",
                        "url": "https://codes.wmo.int/wis/topic-hierarchy/earth-system-discipline/weather"
                    }
                ],
                "scheme": "https://codes.wmo.int/wis/topic-hierarchy/earth-system-discipline"
            }
        ],
        "contacts": [
            {
                "name": "National Inquiry Response Team",
                "organization": "Government of Canada; Environment and Climate Change Canada; Meteorological Service of Canada",
                "phones": [
                    {
                        "value": "+18199972800"
                    }
                ],
                "emails": [
                    {
                        "value": "enviroinfo@ec.gc.ca"
                    }
                ],
                "addresses": [
                    {
                        "deliveryPoint": [
                            "77 Westmorland Street, suite 260"
                        ],
                        "city": "Fredericton",
                        "administrativeArea": "NB",
                        "postalCode": "E3B 6Z4",
                        "country": "Canada"
                    }
                ],
                "links": [
                    {
                        "rel": "about",
                        "type": "text/html",
                        "href": "https://www.canada.ca/en/environment-climate-change.html"
                    }
                ],
                "roles": [
                    "host",
                    "producer"
                ]
            }
        ],
        "type": "dataset",
        "created": "2018-01-01T00:11:32Z",
        "updated": "2022-06-22T08:23:42Z",
        "wmo:dataPolicy": "core"
    },
    "links": [
        {
            "rel": "items",
            "href": "https://api.weather.gc.ca/collections/swob-realtime/items",
            "type": "application/geo+json",
            "title": "Data access API interface"
        },
        {
            "rel": "about",
            "href": "https://eccc-msc.github.io/open-data/msc-data/obs_station/readme_obs_insitu_swobdatamart_en",
            "type": "text/html",
            "title": "Documentation"
        },
        {
            "rel": "items",
            "href": "mqtts://everyone:everyone@globalbroker.meteo.fr:8883",
            "channel": "origin/a/wis2/ca-eccc-msc/data/core/weather/surface-based-observations/synop",
            "type": "application/geo+json",
            "title": "Data notifications"
        }
    ],
    "linkTemplates": [
        {
            "rel": "stations",
            "type": "text/csv",
            "title": "Stations associated with this dataset",
            "uriTemplate": "https://dd.weather.gc.ca/{yyyymmdd}/WXO-DD/observations/doc/swob-xml_station_list.csv",
            "variables": {
                "yyyymmdd": {
                    "type": "string",
                    "description": "date in yyyymmdd format"
                }
            }
        },
        {
            "rel": "data",
            "type": "text/csv",
            "hreflang": "en",
            "title": "Raw data download (CSV files)",
            "uriTemplate": "https://dd.weather.gc.ca/{yyyymmdd}/WXO-DD/observations/swob-ml",
            "variables": {
                "yyyymmdd": {
                    "type": "string",
                    "description": "date in yyyymmdd format"
                }
            }
        }
    ]
}
